{
	"metadata":{
		"name":"modifyinstancenetworkspecrequest",
		"namespace":"aliyunc"
	},
	"apiVersion":"cloudplus.io/v1alpha3",
	"kind":"AliyunC",
	"spec":{
		"lifecycle":{
			"modifyInstanceNetworkSpecRequest":{
				"autoPay":true,
				"allocatePublicIp":true,
				"clientToken":"String",
				"internetMaxBandwidthOut":1,
				"ownerAccount":"String",
				"ownerId":1,
				"internetMaxBandwidthIn":1,
				"instanceId":"String",
				"networkChargeType":"String",
				"resourceOwnerAccount":"String",
				"resourceOwnerId":1,
				"startTime":"String",
				"endTime":"String"
			}
		}
	}
}